setup.py
ilwrathi/__init__.py
ilwrathi/_py2.py
ilwrathi/_py3.py
ilwrathi/iac.py
ilwrathi.egg-info/PKG-INFO
ilwrathi.egg-info/SOURCES.txt
ilwrathi.egg-info/dependency_links.txt
ilwrathi.egg-info/top_level.txt
ilwrathi/_common/__init__.py
ilwrathi/clients/__init__.py