Metadata-Version: 1.1
Name: ilwrathi
Version: 2015.8.dev0
Summary: A framework for building pen test tools
Home-page: https://github.com/jdukes/ilwrathi
Author: Josh Dukes
Author-email: hex@neg9.org
License: GNU General Public License v3 (GPLv3)
Keywords: hacker web CTF pen test
Platform: UNKNOWN
Classifier: Development Status :: 3 - Alpha
Classifier: Intended Audience :: Developers
Classifier: License :: OSI Approved :: GNU General Public License v3 or later (GPLv3+)
Classifier: Natural Language :: English
Classifier: Operating System :: OS Independent
Classifier: Programming Language :: Python :: 2
Classifier: Topic :: Security
Classifier: Topic :: Software Development :: Testing
